pySTIM/__init__.py
pySTIM/_cci.py
pySTIM/_dataset.py
pySTIM/_enrichment.py
pySTIM/_fileIO.py
pySTIM/_processing.py
pySTIM/_sp_plot.py
pySTIM/_utils.py
pySTIM-1.1.6.dist-info/METADATA
pySTIM-1.1.6.dist-info/WHEEL
pySTIM-1.1.6.dist-info/top_level.txt
pySTIM-1.1.6.dist-info/RECORD
