Metadata-Version: 2.1
Name: pySTIM
Version: 1.1.6
Summary: A python package for spatial omics analysis
Home-page: https://github.com/qiaoxy0/STIM
Requires-Dist: anndata
Requires-Dist: scanpy
Requires-Dist: numpy
Requires-Dist: fastparquet
Requires-Dist: pyarrow
Requires-Dist: scipy
Requires-Dist: scikit-learn
Requires-Dist: shapely
Requires-Dist: descartes
Requires-Dist: tifffile
Requires-Dist: opencv-python
Requires-Dist: imagecodecs
Requires-Dist: requests
